[
  {
    "title": "Spotlight on pdfly, the Swiss Army knife for PDF files",
    "source": "Hacker News",
    "url": "https://chezsoi.org/lucas/blog/spotlight-on-pdfly.html",
    "publishedAt": "2025-10-13T08:36:33.000Z",
    "summary": "No description available"
  },
  {
    "title": "HTTP3 Explained",
    "source": "Hacker News",
    "url": "https://http3-explained.haxx.se",
    "publishedAt": "2025-10-13T07:15:28.000Z",
    "summary": "No description available"
  },
  {
    "title": "Countering Trusting Trust Through Diverse Double-Compiling (DDC)",
    "source": "Hacker News",
    "url": "https://dwheeler.com/trusting-trust/",
    "publishedAt": "2025-10-13T02:39:25.000Z",
    "summary": "No description available"
  },
  {
    "title": "For centuries massive meals amazed visitors to Korea (2019)",
    "source": "Hacker News",
    "url": "https://www.atlasobscura.com/articles/history-of-korean-food",
    "publishedAt": "2025-10-13T01:46:18.000Z",
    "summary": "No description available"
  },
  {
    "title": "John Searle has died",
    "source": "Hacker News",
    "url": "https://www.nytimes.com/2025/10/12/books/john-searle-dead.html",
    "publishedAt": "2025-10-13T00:57:49.000Z",
    "summary": "No description available"
  },
  {
    "title": "Novelty Automation",
    "source": "Hacker News",
    "url": "https://www.novelty-automation.com/",
    "publishedAt": "2025-10-12T23:46:55.000Z",
    "summary": "No description available"
  },
  {
    "title": "Free software hasn't won",
    "source": "Hacker News",
    "url": "https://dorotac.eu/posts/fosswon/",
    "publishedAt": "2025-10-12T21:51:45.000Z",
    "summary": "No description available"
  },
  {
    "title": "An initial investigation into WDDM on ReactOS",
    "source": "Hacker News",
    "url": "https://reactos.org/blogs/investigating-wddm/",
    "publishedAt": "2025-10-12T21:40:43.000Z",
    "summary": "No description available"
  },
  {
    "title": "MAML – A new configuration language",
    "source": "Hacker News",
    "url": "https://maml.dev/",
    "publishedAt": "2025-10-12T21:24:39.000Z",
    "summary": "No description available"
  },
  {
    "title": "Emacs agent-shell (powered by ACP)",
    "source": "Hacker News",
    "url": "https://xenodium.com/introducing-agent-shell",
    "publishedAt": "2025-10-12T20:37:16.000Z",
    "summary": "Also: https:&#x2F;&#x2F;xenodium.com&#x2F;agent-shell-0-5-improvements..."
  },
  {
    "title": "Completing a BASIC language interpreter in 2025",
    "source": "Hacker News",
    "url": "https://nanochess.org/ecs_basic_2.html",
    "publishedAt": "2025-10-12T19:19:38.000Z",
    "summary": "No description available"
  },
  {
    "title": "Constraint satisfaction to optimize item selection for bundles in Minecraft",
    "source": "Hacker News",
    "url": "https://www.robw.fyi/2025/10/12/using-constraint-satisfaction-to-optimize-item-selection-for-bundles-in-minecraft/",
    "publishedAt": "2025-10-12T18:31:51.000Z",
    "summary": "No description available"
  },
  {
    "title": "Wireguard FPGA",
    "source": "Hacker News",
    "url": "https://github.com/chili-chips-ba/wireguard-fpga",
    "publishedAt": "2025-10-12T17:12:00.000Z",
    "summary": "No description available"
  },
  {
    "title": "A years-long Turkish alphabet bug in the Kotlin compiler",
    "source": "Hacker News",
    "url": "https://sam-cooper.medium.com/the-country-that-broke-kotlin-84bdd0afb237",
    "publishedAt": "2025-10-12T17:02:09.000Z",
    "summary": "No description available"
  },
  {
    "title": "Show HN: I built a simple ambient sound app with no ads or subscriptions",
    "source": "Hacker News",
    "url": "https://ambisounds.app/",
    "publishedAt": "2025-10-12T14:49:50.000Z",
    "summary": "I’ve always liked having background noise while working or falling asleep, but I got frustrated that most “white noise” or ambient sound apps are eith..."
  },
  {
    "title": "Three ways formally verified code can go wrong in practice",
    "source": "Hacker News",
    "url": "https://buttondown.com/hillelwayne/archive/three-ways-formally-verified-code-can-go-wrong-in/",
    "publishedAt": "2025-10-12T06:17:52.000Z",
    "summary": "No description available"
  },
  {
    "title": "New Dissidia Final Fantasy title for iOS, Android to be announced on October 14 - Gematsu",
    "source": "Gematsu",
    "url": "https://www.gematsu.com/2025/10/new-dissidia-final-fantasy-title-for-ios-android-to-be-announced-on-october-14",
    "publishedAt": "2025-10-12T03:10:57Z",
    "summary": "Square Enix will announce a new Dissidia Final Fantasy title for iOS and Android on October 14 at 3:00 a.m. PT / 6:00 a.m. ET / 19:00 JST, the company announced. You will be able to watch the &#822…",
    "imageUrl": "https://www.gematsu.com/wp-content/uploads/2025/10/New-Dissidia_10-12-25.jpg"
  },
  {
    "title": "iOS 26.0.2 coming soon for iPhone users - 9to5Mac",
    "source": "9to5Mac",
    "url": "https://9to5mac.com/2025/10/11/ios-26-0-2-coming-soon-for-iphone-users/",
    "publishedAt": "2025-10-12T02:55:00Z",
    "summary": "After releasing iOS 26 to the general public around a month ago, Apple is now preparing its second bug fix...",
    "imageUrl": "https://i0.wp.com/9to5mac.com/wp-content/uploads/sites/6/2025/06/iOS-26-hero-02.jpg?resize=1200%2C628&quality=82&strip=all&ssl=1"
  },
  {
    "title": "AT&T Website References Next-Generation iPad Pro With M5 Chip - MacRumors",
    "source": "MacRumors",
    "url": "https://www.macrumors.com/2025/10/11/att-website-references-next-generation-ipad-pro-with-m5-chip/",
    "publishedAt": "2025-10-12T02:36:42Z",
    "summary": "AT&T's website references an unreleased iPad Pro model with an M5 chip, but it is unclear if it is an accidental leak, or simply a premature...",
    "imageUrl": "https://images.macrumors.com/t/fXHx_BozuNUEWL-lX7vYEtHEY1I=/3840x/article-new/2024/05/ipad-pro-2024.jpg"
  },
  {
    "title": "Journalist Hacks Card Shuffling Machine to Prove How to Cheat in Poker - PokerNews",
    "source": "PokerNews.com",
    "url": "https://www.pokernews.com/news/2025/10/journalist-hacks-card-shuffler-to-prove-cheating-49845.htm",
    "publishedAt": "2025-10-11T21:50:00Z",
    "summary": "WIRED Senior Writer Andy Greenberg explored the vulnerabilities of shuffling machines.",
    "imageUrl": "https://pnimg.net/w/articles/0/68e/abb5f71c72.jpg"
  },
  {
    "title": "Xbox Controllers Are Now Selling for Pennies, Microsoft Is Offloading Prime Day Leftovers - Kotaku",
    "source": "Kotaku",
    "url": "https://kotaku.com/xbox-controllers-are-now-selling-for-pennies-microsoft-is-offloading-prime-day-leftovers-2000634423",
    "publishedAt": "2025-10-11T21:15:12Z",
    "summary": "This 2025 Xbox controller has never been more affordable.",
    "imageUrl": "https://kotaku.com/app/uploads/2025/08/xbox-controller-1200x675.jpg"
  },
  {
    "title": "A whirlwind introduction to dataflow graphs (2018)",
    "source": "Hacker News",
    "url": "https://fgiesen.wordpress.com/2018/03/05/a-whirlwind-introduction-to-dataflow-graphs/",
    "publishedAt": "2025-10-11T20:52:21.000Z",
    "summary": "No description available"
  },
  {
    "title": "11 Budget-Friendly Cars From The Golden Era Of American Muscle - Jalopnik",
    "source": "Jalopnik",
    "url": "https://www.jalopnik.com/1992156/budget-friendly-classic-muscle-cars/",
    "publishedAt": "2025-10-11T20:45:00Z",
    "summary": "Owning a piece of automotive history from the heyday of American muscle cars doesn't have to cost a fortune. Here are some options that won't break the bank.",
    "imageUrl": "https://www.jalopnik.com/img/gallery/11-budget-friendly-cars-from-the-golden-era-of-american-muscle/l-intro-1760040132.jpg"
  },
  {
    "title": "Are You Mean When You're Overstimulated? There's Actually A Reason For That. - Yahoo Life UK",
    "source": "Buzzfeed",
    "url": "https://www.buzzfeed.com/jillianwilson/experts-say-this-why-youre-mean-when-overstimulated-sc",
    "publishedAt": "2025-10-11T20:31:02Z",
    "summary": "No, you're not a bad person. Here's what's really going on, according to science.",
    "imageUrl": "https://s.yimg.com/ny/api/res/1.2/9GT2rTug7i2jyFrylvKv7w--/YXBwaWQ9aGlnaGxhbmRlcjt3PTEyMDA7aD03OTc7Y2Y9d2VicA--/https://media.zenfs.com/en/buzzfeed_articles_778/cd098e0c2bed71179a2537f80d64460a"
  },
  {
    "title": "Super Mario Galaxy 2 on Nintendo Switch removes an NPC from the Wii original - Nintendo Everything",
    "source": "Nintendoeverything.com",
    "url": "https://nintendoeverything.com/super-mario-galaxy-2-on-nintendo-switch-removes-an-npc/",
    "publishedAt": "2025-10-11T20:01:50Z",
    "summary": "File this one under slightly random, but fans have noticed that the new Nintendo Switch version of Super Mario Galaxy has replaced one of its NPCs. In the Wii original, Starship Mario had a specific Toad you could interact with to deposit Starbits. This allow…",
    "imageUrl": "https://nintendoeverything.com/wp-content/uploads/Super-Mario-Galaxy-2-NPC-removed.jpg"
  },
  {
    "title": "Bethesda Teases New Game (And It May Be Bringing Back Series We Haven't Seen Since the 2010s) - ComicBook.com",
    "source": "ComicBook.com",
    "url": "http://comicbook.com/gaming/news/bethesda-teases-new-game-and-it-may-be-bringing-series-we-havent-seen-since-the-2010s/",
    "publishedAt": "2025-10-11T19:35:56Z",
    "summary": "Bethesda is teasing a new game, and it appears to be a new installment in a series we have not seen since the 2010s.",
    "imageUrl": "https://comicbook.com/wp-content/uploads/sites/4/2025/10/w-o-l-f-e-n-s-t-e-i-n.png?resize=2000,1125"
  },
  {
    "title": "Apple ends support for Clips video-editing app - The Verge",
    "source": "The Verge",
    "url": "https://www.theverge.com/news/798676/apple-ends-support-for-clips-video-editing-app",
    "publishedAt": "2025-10-11T19:35:04Z",
    "summary": "As of October 10th Clips will no longer receive updates and won’t be available to download from the App Store.",
    "imageUrl": "https://platform.theverge.com/wp-content/uploads/sites/2/2025/10/Clips3.webp?quality=90&strip=all&crop=0%2C11.044304996833%2C100%2C77.911390006335&w=1200"
  },
  {
    "title": "Fan creates Switch-style dock making Nintendo 3DS playable on TV - GoNintendo",
    "source": "GoNintendo",
    "url": "https://gonintendo.com/contents/53816-fan-creates-switch-style-dock-making-nintendo-3ds-playable-on-tv",
    "publishedAt": "2025-10-11T18:10:55Z",
    "summary": "Gives a whole new meaning to 3D TV",
    "imageUrl": "https://gonintendo.com/attachments/image/71842/file/medium-7e462b60406a98747ebb01ca2d2ae902.png"
  },
  {
    "title": "iPhone 18 Pro Already Rumored to Have These 6 New Features - MacRumors",
    "source": "MacRumors",
    "url": "https://www.macrumors.com/2025/10/11/iphone-18-pro-features-rumors/",
    "publishedAt": "2025-10-11T17:10:00Z",
    "summary": "While the iPhone 18 Pro and iPhone 18 Pro Max are still nearly a year away, a handful of new features and changes have already been rumored for the...",
    "imageUrl": "https://images.macrumors.com/t/ifxwRcZgwvurs4DL1GejlAlvKQA=/1600x/article-new/2025/09/iPhone-17-Pro-Colors.jpg"
  },
  {
    "title": "Pokemon Legends: Z-A leaks starting, new Mega Evolutions shown - Nintendo Everything",
    "source": "Nintendoeverything.com",
    "url": "https://nintendoeverything.com/pokemon-legends-z-a-leaks-mega-evolutions/",
    "publishedAt": "2025-10-11T16:46:50Z",
    "summary": "Pokemon Legends: Z-A is only a few days away from launch, and leaks are now starting to happen, including a look at some new Mega Evolutions. If you’ve kept up with pre-release happenings for Pokemon games, you probably know that information tends to come out…",
    "imageUrl": "https://nintendoeverything.com/wp-content/uploads/Pokemon-Legends-Z-A-leaks-Mega-Evolutions.jpg"
  },
  {
    "title": "How The Outer Worlds 2 is being shaped by Ninja Theory, Double Fine, and other Xbox studios - Windows Central",
    "source": "Windows Central",
    "url": "https://www.windowscentral.com/gaming/xbox/the-outer-worlds-2-directors-talk-ninja-theory-future-games",
    "publishedAt": "2025-10-11T16:41:06Z",
    "summary": "From motion capture lessons to gunplay tweaks, Obsidian’s directors explain how collaboration across Xbox is influencing both The Outer Worlds 2 and future projects.",
    "imageUrl": "https://cdn.mos.cms.futurecdn.net/RtYmDzEZ3Z6GZDb6o8Zf63-1920-80.jpg"
  },
  {
    "title": "Scientists Achieved Teleportation Using Quantum Supercomputers - Here's How - bgr.com",
    "source": "BGR",
    "url": "https://www.bgr.com/1988900/how-scientists-achieved-teleportation-quantum-supercomputers/",
    "publishedAt": "2025-10-11T16:17:00Z",
    "summary": "Despite sounding like sci-fi, teleportation is a very real thing. However, it might not be the kind of teleportation that you've seen in TV shows and movies.",
    "imageUrl": "https://www.bgr.com/img/gallery/scientists-achieved-teleportation-using-quantum-supercomputers-heres-how/l-intro-1759530148.jpg"
  },
  {
    "title": "I swapped the Apple Watch Ultra 3 for the Apple Watch Series 11 — here’s my pros and cons - Tom's Guide",
    "source": "Tom's Guide",
    "url": "https://www.tomsguide.com/wellness/smartwatches/i-swapped-my-apple-watch-ultra-3-for-the-apple-watch-series-11-heres-3-things-i-liked-and-3-things-i-missed",
    "publishedAt": "2025-10-11T15:48:17Z",
    "summary": "Which Apple Watch should you buy?",
    "imageUrl": "https://cdn.mos.cms.futurecdn.net/bA29BXcdZ93dHQknagYCY-2560-80.jpg"
  },
  {
    "title": "Here's the Latest on Apple Suing Jon Prosser Over iOS 26 Leaks - MacRumors",
    "source": "MacRumors",
    "url": "https://www.macrumors.com/2025/10/11/apple-jon-prosser-lawsuit-latest-updates/",
    "publishedAt": "2025-10-11T15:15:43Z",
    "summary": "In July, Apple filed a lawsuit against Jon Prosser and Michael Ramacciotti over alleged theft of the company's trade secrets. The complaint...",
    "imageUrl": "https://images.macrumors.com/t/oCYEjeWdNk0EevfzJBuDMrnlqcA=/1600x/article-new/2025/10/Jon-Prosser-Rainbow.jpg"
  },
  {
    "title": "The AirPods 4 and Lego’s brick-ified Grogu are our favorite deals this week - The Verge",
    "source": "The Verge",
    "url": "https://www.theverge.com/tech/798362/apple-airpods-4-lego-star-wars-grogu-deal-sale",
    "publishedAt": "2025-10-11T15:01:53Z",
    "summary": "You can score the AirPods 4 for 31 percent off right now. There are also deals available on an adorable Lego Star Wars Grogu set and Philips Hue smart bulbs.",
    "imageUrl": "https://platform.theverge.com/wp-content/uploads/sites/2/2025/10/Apple-AirPods-4-deal.png?quality=90&strip=all&crop=0%2C10.732984293194%2C100%2C78.534031413613&w=1200"
  },
  {
    "title": "Wyze is making the clever cameras I wish Google Nest would [Gallery] - 9to5Google",
    "source": "9to5google.com",
    "url": "http://9to5google.com/2025/10/11/wyze-is-still-making-the-clever-cameras-i-wish-google-nest-would/",
    "publishedAt": "2025-10-11T14:45:00Z",
    "summary": "Home security cameras are commonplace at this point, but there’s something to be said about the ingenuity in the space....",
    "imageUrl": "https://i0.wp.com/9to5google.com/wp-content/uploads/sites/4/2025/10/wyze-bulb-duo-cams-1.jpg?resize=1200%2C628&quality=82&strip=all&ssl=1"
  },
  {
    "title": "Nintendo Has Been Reportedly Hacked, Known Hacking Group Claims - Wccftech",
    "source": "Wccftech",
    "url": "https://wccftech.com/nintendo-has-been-reportedly-hacked-known-hacking-group-claims/",
    "publishedAt": "2025-10-11T14:03:00Z",
    "summary": "The Crimson Collective hacking group is claiming to have hacked Nintendo, according to a new online report shared today.",
    "imageUrl": "https://cdn.wccftech.com/wp-content/uploads/2025/10/Nintendo-HD-scaled-1.jpg"
  },
  {
    "title": "‘Borderlands 4’ Reveals Bounty Pack, Invincible Boss Release Dates, New Loot - Forbes",
    "source": "Forbes",
    "url": "https://www.forbes.com/sites/paultassi/2025/10/11/borderlands-4-reveals-bounty-pack-invincible-boss-release-dates-new-loot/",
    "publishedAt": "2025-10-11T12:42:57Z",
    "summary": "Here's what's coming in Borderlands 4's, first three content packs from loot to skins, and their release dates.",
    "imageUrl": "https://imageio.forbes.com/specials-images/imageserve/68ea5013ec401b7eb053f2b5/0x0.jpg?format=jpg&height=900&width=1600&fit=bounds"
  },
  {
    "title": "One-click theme packs are coming to Android thanks to Google's new Theme Manager - Android Authority",
    "source": "Android Authority",
    "url": "https://www.androidauthority.com/android-theme-manager-3606395/",
    "publishedAt": "2025-10-11T12:23:28Z",
    "summary": "Google is creating theme packs for Pixel phones, and to make them work, it’s developed a new Theme Manager for Android. Here’s how it works.",
    "imageUrl": "https://www.androidauthority.com/wp-content/uploads/2025/10/Photo-of-Android-lock-screen-customization-on-Pixel-phone-scaled.jpg"
  },
  {
    "title": "14 unusual Android apps I always install on my phone - Android Authority",
    "source": "Android Authority",
    "url": "https://www.androidauthority.com/unusual-android-apps-3605365/",
    "publishedAt": "2025-10-11T12:11:18Z",
    "summary": "We all have our best Android apps, but what about those apps that fulfill unique needs? I look at the unusual Android apps I always install.",
    "imageUrl": "https://www.androidauthority.com/wp-content/uploads/2025/10/whobird-unusual-android-app-2.jpg"
  },
  {
    "title": "Battlefield 6 has only been out a day and it's already one of Steam's biggest games ever - Eurogamer",
    "source": "Eurogamer.net",
    "url": "https://www.eurogamer.net/battlefield-6-has-only-been-out-a-day-and-its-already-one-of-steams-biggest-games-ever",
    "publishedAt": "2025-10-11T12:09:34Z",
    "summary": "Battlefield 6 has rocketed into Steam's chart of the biggest-ever games, becoming Steam's fourteenth most-popular game …",
    "imageUrl": "https://assetsio.gnwcdn.com/Battlefield-6-Official-Reveal-Trailer-0-58-screenshot.png?width=1200&height=630&fit=crop&enable=upscale&auto=webp"
  },
  {
    "title": "Excuse Me?!? Anbernic RG DS Will Cost Under $100! - Retro Handhelds",
    "source": "Retrohandhelds.gg",
    "url": "https://retrohandhelds.gg/excuse-me-anbernic-rg-ds-will-cost-under-100/",
    "publishedAt": "2025-10-11T11:50:26Z",
    "summary": "The Anbernic RG DS is coming: dual screens, under $100, and touchscreen support. Anbernic might have a holiday best-seller on its hands.",
    "imageUrl": "https://rh-handhelds-content.nyc3.cdn.digitaloceanspaces.com/2025/10/Anbernic-RG-DS-Colors-Overview.jpg"
  },
  {
    "title": "I compared 5G network signals of Verizon, T-Mobile, and AT&T at a baseball stadium - here's the winner - ZDNET",
    "source": "ZDNet",
    "url": "https://www.zdnet.com/article/i-compared-5g-network-signals-of-verizon-t-mobile-and-at-t-at-a-baseball-stadium-heres-the-winner/",
    "publishedAt": "2025-10-11T10:30:00Z",
    "summary": "With three Google Pixel 10 Pro phones in hand, here's how each carrier fared as I made my way throughout the stadium.",
    "imageUrl": "https://www.zdnet.com/a/img/resize/71fcb42d63bd908a702a93bffb6f3a6fbae68098/2025/10/10/cd1615e2-b877-4dc5-a329-7531c7a19f4a/pxl-20251001-194636931.jpg?auto=webp&fit=crop&height=675&width=1200"
  },
  {
    "title": "We Swear By Blates For Hearty Weeknight Dinners—And These 10 Sets Are On Sale, Starting At $5 Apiece - Southern Living",
    "source": "Southernliving.com",
    "url": "https://www.southernliving.com/amazon-blate-deals-2025-11828001",
    "publishedAt": "2025-10-11T10:00:00Z",
    "summary": "It’s soup and pasta season! Blates are an underrated must-have for cutting down on dishes thanks to their plate/bowl hybrid design. Shop these 10 sets from Amazon while they’re on sale, starting at $30.",
    "imageUrl": "https://www.southernliving.com/thmb/iZ9p91Qg-5jCFIyLsVwkhPOCX9w=/1500x0/filters:no_upscale():max_bytes(150000):strip_icc()/slv-freelance-roundup-amazon-blate-deals-tout-81c1bc4f3b9043e7988a6bba4b0c86d4.jpg"
  },
  {
    "title": "Hydrapple Quick PvP Analysis: Stats, Moves, and First Impressions - Pokémon GO Hub",
    "source": "Pokemon GO Hub",
    "url": "https://pokemongohub.net/post/pvp/hydrapple-pvp-analysis/",
    "publishedAt": "2025-10-11T09:23:54Z",
    "summary": "Hydrapple has finally arrived in Pokémon GO, introducing a new Grass and Dragon-type contender to the PvP scene. With strong overall stats, solid typing, and a familiar move pool, many Trainers are wondering if Hydrapple can outperform its relatives like Flap…",
    "imageUrl": "https://pokemongohub.net/wp-content/uploads/2025/10/8qo6hjw.png"
  },
  {
    "title": "3D-Printed Automatic Weather Station",
    "source": "Hacker News",
    "url": "https://3dpaws.comet.ucar.edu",
    "publishedAt": "2025-10-09T15:45:49.000Z",
    "summary": "No description available"
  },
  {
    "title": "Keyboard Holders, Generation 1",
    "source": "Hacker News",
    "url": "https://cceckman.com/writing/keyboard-holders-gen1/",
    "publishedAt": "2025-10-09T15:29:31.000Z",
    "summary": "No description available"
  },
  {
    "title": "MicroPythonOS – An Android-like OS for microcontrollers",
    "source": "Hacker News",
    "url": "https://micropythonos.com",
    "publishedAt": "2025-10-09T10:35:40.000Z",
    "summary": "No description available"
  },
  {
    "title": "A better SQL validator and comparison with existing SQL validators",
    "source": "Hacker News",
    "url": "https://app.sqlai.ai/posts/better-sql-validator/",
    "publishedAt": "2025-10-08T16:25:40.000Z",
    "summary": "No description available"
  },
  {
    "title": "Show HN: Baby's first international landline",
    "source": "Hacker News",
    "url": "https://wip.tf/posts/telefonefix-building-babys-first-international-landline/",
    "publishedAt": "2025-10-08T13:31:35.000Z",
    "summary": "Hi HN,As a weekend project, I hacked together a physical phone, a Raspberry Pi running Asterisk and Twilio, to let toddlers safely make international ..."
  },
  {
    "title": "The Tiny Teams Playbook",
    "source": "Hacker News",
    "url": "https://www.latent.space/p/tiny",
    "publishedAt": "2025-10-08T12:50:32.000Z",
    "summary": "No description available"
  },
  {
    "title": "Database Linting and Analysis for PostgreSQL",
    "source": "Hacker News",
    "url": "https://pglinter.readthedocs.io/en/latest/",
    "publishedAt": "2025-10-08T08:09:07.000Z",
    "summary": "No description available"
  },
  {
    "title": "Tauri binding for Python through Pyo3",
    "source": "Hacker News",
    "url": "https://github.com/pytauri/pytauri",
    "publishedAt": "2025-10-08T06:58:00.000Z",
    "summary": "No description available"
  },
  {
    "title": "Putting a Dumb Weather Station on the Internet",
    "source": "Hacker News",
    "url": "https://colincogle.name/blog/byo-weather-station/",
    "publishedAt": "2025-10-07T19:11:04.000Z",
    "summary": "No description available"
  },
  {
    "title": "Jeffrey Hudson the Court Dwarf of the English Queen Henrietta Maria of France",
    "source": "Hacker News",
    "url": "https://en.wikipedia.org/wiki/Jeffrey_Hudson",
    "publishedAt": "2025-10-07T17:51:46.000Z",
    "summary": "No description available"
  },
  {
    "title": "Bird photographer of the year gives a lesson in planning and patience",
    "source": "Hacker News",
    "url": "https://www.thisiscolossal.com/2025/09/2025-bird-photographer-of-the-year-contest/",
    "publishedAt": "2025-10-06T02:53:17.000Z",
    "summary": "No description available"
  }
]